ceviche_challenges/__init__.py
ceviche_challenges/defs.py
ceviche_challenges/defs_test.py
ceviche_challenges/model_base.py
ceviche_challenges/modes.py
ceviche_challenges/modes_test.py
ceviche_challenges/ops.py
ceviche_challenges/ops_test.py
ceviche_challenges/params.py
ceviche_challenges/primitives.py
ceviche_challenges/primitives_test.py
ceviche_challenges/scattering.py
ceviche_challenges/scattering_test.py
ceviche_challenges/units.py
ceviche_challenges/beam_splitter/__init__.py
ceviche_challenges/beam_splitter/model.py
ceviche_challenges/beam_splitter/model_test.py
ceviche_challenges/beam_splitter/prefabs.py
ceviche_challenges/beam_splitter/spec.py
ceviche_challenges/mode_converter/__init__.py
ceviche_challenges/mode_converter/model.py
ceviche_challenges/mode_converter/model_test.py
ceviche_challenges/mode_converter/prefabs.py
ceviche_challenges/mode_converter/spec.py
ceviche_challenges/waveguide_bend/__init__.py
ceviche_challenges/waveguide_bend/model.py
ceviche_challenges/waveguide_bend/model_test.py
ceviche_challenges/waveguide_bend/prefabs.py
ceviche_challenges/waveguide_bend/spec.py
ceviche_challenges/wdm/__init__.py
ceviche_challenges/wdm/model.py
ceviche_challenges/wdm/model_test.py
ceviche_challenges/wdm/prefabs.py
ceviche_challenges/wdm/spec.py
ceviche_challenges-1.0.2.dist-info/LICENSE
ceviche_challenges-1.0.2.dist-info/METADATA
ceviche_challenges-1.0.2.dist-info/WHEEL
ceviche_challenges-1.0.2.dist-info/top_level.txt
ceviche_challenges-1.0.2.dist-info/RECORD
